<?xml version="1.0" encoding="utf-8"?>
<!DOCTYPE Map>
<Map srs="+proj=longlat +ellps=WGS84 +datum=WGS84 +no_defs">




    <Style name="raster">
      <Rule>
	<RasterSymbolizer>
	</RasterSymbolizer>
      </Rule>
    </Style>

<Layer name="dem-N45E006" srs="+proj=longlat +ellps=WGS84 +datum=WGS84 +no_defs">
	<StyleName>raster</StyleName>
	<Datasource>
		<Parameter name="type">gdal</Parameter>
		<Parameter name="file">/home/bluekulu/Development/mapniktest/test/TrueMarble.16km.2700x1350.tif</Parameter>
		<Parameter name="format">tiff</Parameter>
	</Datasource>
</Layer>

<Layer name="dem-N45E006" srs="+proj=longlat +ellps=WGS84 +datum=WGS84 +no_defs">
	<StyleName>raster</StyleName>
	<Datasource>
		<Parameter name="type">gdal</Parameter>
		<Parameter name="file">/home/bluekulu/Development/mapniktest/test/d_OSI_50000_Raster_IG_modified.tif</Parameter>
		<Parameter name="format">tiff</Parameter>
	</Datasource>
</Layer>


</Map>
